CHANGES.rst
LICENSE.txt
MANIFEST.in
README.rst
setup.py
version.txt
nssjson/__init__.py
nssjson/_speedups.c
nssjson/compat.py
nssjson/decoder.py
nssjson/encoder.py
nssjson/ordered_dict.py
nssjson/scanner.py
nssjson/tool.py
nssjson.egg-info/PKG-INFO
nssjson.egg-info/SOURCES.txt
nssjson.egg-info/dependency_links.txt
nssjson.egg-info/top_level.txt
nssjson/tests/__init__.py
nssjson/tests/test_bigint_as_string.py
nssjson/tests/test_check_circular.py
nssjson/tests/test_datetime.py
nssjson/tests/test_decimal.py
nssjson/tests/test_decode.py
nssjson/tests/test_default.py
nssjson/tests/test_dump.py
nssjson/tests/test_encode_basestring_ascii.py
nssjson/tests/test_encode_for_html.py
nssjson/tests/test_errors.py
nssjson/tests/test_fail.py
nssjson/tests/test_float.py
nssjson/tests/test_for_json.py
nssjson/tests/test_indent.py
nssjson/tests/test_item_sort_key.py
nssjson/tests/test_namedtuple.py
nssjson/tests/test_pass1.py
nssjson/tests/test_pass2.py
nssjson/tests/test_pass3.py
nssjson/tests/test_recursion.py
nssjson/tests/test_scanstring.py
nssjson/tests/test_separators.py
nssjson/tests/test_speedups.py
nssjson/tests/test_subclass.py
nssjson/tests/test_tool.py
nssjson/tests/test_tuple.py
nssjson/tests/test_unicode.py
nssjson/tests/test_uuid.py